MANIFEST.in
MIT-LICENSE.txt
README.rst
setup.py
country_dialcode/__init__.py
country_dialcode/__init__.pyc
country_dialcode/admin.py
country_dialcode/admin.pyc
country_dialcode/app_label_renamer.pyc
country_dialcode/apps.py
country_dialcode/apps.pyc
country_dialcode/compatibility.py
country_dialcode/compatibility.pyc
country_dialcode/forms.py
country_dialcode/intermediate_model_base_class.py
country_dialcode/intermediate_model_base_class.pyc
country_dialcode/models.py
country_dialcode/models.pyc
country_dialcode/urls.py
country_dialcode/utils.py
country_dialcode/views.py
country_dialcode/fixtures/country_dialcode.json
country_dialcode/management/__init__.py
country_dialcode/management/__init__.pyc
country_dialcode/management/commands/__init__.py
country_dialcode/management/commands/__init__.pyc
country_dialcode/management/commands/load_country_dialcode.py
country_dialcode/management/commands/load_country_dialcode.pyc
country_dialcode/not_sql/country.sql
country_dialcode/not_sql/prefix.sql
country_dialcode/templatetags/__init__.py
country_dialcode/templatetags/__init__.pyc
country_dialcode/templatetags/country_dialcode_tags.py
country_dialcode/templatetags/country_dialcode_tags.pyc
country_dialcode/tests/__init__.py
country_dialcode/tests/__init__.pyc
country_dialcode/tests/runtests.py
country_dialcode/tests/test_settings.py
country_dialcode/tests/test_settings.pyc
country_dialcode/tests/tests.py
country_dialcode/tests/tests.pyc
country_dialcode/tests/utils.py
country_dialcode/tests/utils.pyc
country_dialcode/utils/__init__.py
country_dialcode/utils/__init__.pyc
country_dialcode/utils/isoflag.py
country_dialcode/utils/isoflag.pyc
django_country_dialcode.egg-info/PKG-INFO
django_country_dialcode.egg-info/SOURCES.txt
django_country_dialcode.egg-info/dependency_links.txt
django_country_dialcode.egg-info/not-zip-safe
django_country_dialcode.egg-info/top_level.txt